xss_protector/__init__.py
xss_protector/decorator/__init__.py
xss_protector/decorator/xss_protector.py
xss_protector/utils/__init__.py
xss_protector/utils/exclude_fields.py
xss_protector/utils/filter_fields.py
xss_protector/utils/silent_delete_from_dictionary.py
django_xss_protector-1.0.4.dist-info/LICENSE
django_xss_protector-1.0.4.dist-info/METADATA
django_xss_protector-1.0.4.dist-info/WHEEL
django_xss_protector-1.0.4.dist-info/top_level.txt
django_xss_protector-1.0.4.dist-info/RECORD
