Metadata-Version: 2.1
Name: django-xss-protector
Version: 1.0.4
License-File: LICENSE
